{
  "fullscreenContainer": {
    "flex": 1,
    "flexDirection": "column",
    "backgroundColor": "rgba(0, 0, 0, 0.8)"
  },
  
  "container": {
    "flex": 1,
    "flexDirection": "column",
    "alignItems": "flex-end"
  },

  "dismissButtonTopRight":{
    "position": "absolute",
    "top": 15,
    "right": 15,
  },

  "rowCenter": {
    "flex": 1,
    "flexDirection": "row",
    "alignSelf": "center",
    "backgroundColor": "transparent",
  },

  "rowBottom": {
    "flex":1,
    "flexDirection": "row",
    "alignSelf": "center",
    "alignItems": "flex-end",
    "backgroundColor": "transparent",
  },

  "icon": {
    "textAlign": "center",
    "margin": 15
  },

  "closeIconStyle": {
    "fontSize": 20,
    "textAlign": "center",
    "color": "#8E8E8E",
    "fontFamily": "fontawesome",
  },
}